LICENSE
README.md
pyproject.toml
pyrefine/__init__.py
pyrefine/adaptation_driver.py
pyrefine/component_base.py
pyrefine/directory_utils.py
pyrefine/shell_utils.py
pyrefine.egg-info/PKG-INFO
pyrefine.egg-info/SOURCES.txt
pyrefine.egg-info/dependency_links.txt
pyrefine.egg-info/entry_points.txt
pyrefine.egg-info/requires.txt
pyrefine.egg-info/top_level.txt
pyrefine/controller/__init__.py
pyrefine/controller/aoa_sweep.py
pyrefine/controller/base.py
pyrefine/controller/basic.py
pyrefine/controller/monitor_forces.py
pyrefine/controller/monitor_quantity.py
pyrefine/controller/node_ratio.py
pyrefine/controller/smooth_transition.py
pyrefine/controller/trimmed_lfd.py
pyrefine/monitoring/__init__.py
pyrefine/monitoring/plotly_base.py
pyrefine/monitoring/pr_gui_fun3d_sfe_steady.py
pyrefine/monitoring/pr_gui_fun3d_sfe_steady_adjoint.py
pyrefine/monitoring/pr_gui_fun3d_steady.py
pyrefine/monitoring/pr_gui_fun3d_steady_live.py
pyrefine/monitoring/pr_watch.py
pyrefine/post_processing/__init__.py
pyrefine/post_processing/fun3d_file_reader.py
pyrefine/post_processing/post_processing_command.py
pyrefine/post_processing/pr_post_fun3d_steady_hist_to_tec.py
pyrefine/post_processing/sfe_file_reader.py
pyrefine/post_processing/tecplot_writer.py
pyrefine/refine/__init__.py
pyrefine/refine/aflr3.py
pyrefine/refine/base.py
pyrefine/refine/bootstrap.py
pyrefine/refine/goal_oriented.py
pyrefine/refine/helden_multiscale.py
pyrefine/refine/multiscale.py
pyrefine/refine/tinfinity_multiscale.py
pyrefine/refine/uniform_region.py
pyrefine/simulation/__init__.py
pyrefine/simulation/base.py
pyrefine/simulation/distance_base.py
pyrefine/simulation/distance_refine.py
pyrefine/simulation/distance_tinf.py
pyrefine/simulation/fun3d.py
pyrefine/simulation/fun3d_adjoint.py
pyrefine/simulation/fun3d_flutter.py
pyrefine/simulation/fun3d_lfd.py
pyrefine/simulation/fun3d_two_phase_unsteady.py
pyrefine/simulation/sfe_cfg.py
pyrefine/simulation/sfe_cfg_update.py