Metadata-Version: 2.4
Name: pyrefine
Version: 1.1.1
Summary: Python scripting for CFD mesh adaptation with refine
Author-email: Kevin Jacobson <kevin.e.jacobson@nasa.gov>
License: NASA OPEN SOURCE AGREEMENT VERSION 1.3
Requires-Python: >=3.7
License-File: LICENSE
Requires-Dist: numpy
Requires-Dist: f90nml
Requires-Dist: pbs4py
Dynamic: license-file
